v2dl_lite/__init__.py
v2dl_lite/__main__.py
v2dl_lite/_types.py
v2dl_lite/constant.py
v2dl_lite/downloader.py
v2dl_lite/logger.py
v2dl_lite/options.py
v2dl_lite/scrapper.py
v2dl_lite/utils.py
v2dl_lite/version.py
v2dl_lite-0.1.4.dist-info/METADATA
v2dl_lite-0.1.4.dist-info/WHEEL
v2dl_lite-0.1.4.dist-info/entry_points.txt
v2dl_lite-0.1.4.dist-info/licenses/LICENSE
v2dl_lite-0.1.4.dist-info/RECORD
