Metadata-Version: 2.3
Name: v2dl-lite
Version: 0.1.4
Summary: A super lightweight version of V2PH downloader
Project-URL: repository, https://github.com/ZhenShuo2021/V2DL-Lite
Project-URL: homepage, https://github.com/ZhenShuo2021/V2PH-Lite
Author-email: ZhenShuo2021 <leo01412123@gmail.com>
License: MIT License
Requires-Python: >=3.10
Requires-Dist: colorama>=0.4.6
Requires-Dist: curl-cffi>=0.7.3
Requires-Dist: httpx[http2]>=0.27.2
Requires-Dist: lxml>=5.3.0
Requires-Dist: pathvalidate>=3.2.1
Provides-Extra: ja4
Requires-Dist: primp>=0.8.1; extra == 'ja4'
Provides-Extra: v2dl
Requires-Dist: v2dl>=0.1.6; extra == 'v2dl'
